lincs_cookiecutter/__init__.py
lincs_cookiecutter/lincs_cookiecutter.py
lincs_cookiecutter/sub_package_1/__init__.py
lincs_cookiecutter/sub_package_1/my_class_1.py
lincs_cookiecutter/sub_package_2/__init__.py
lincs_cookiecutter/sub_package_2/my_class_2.py
lincs_cookiecutter/sub_package_2/my_class_3.py
tests/__init__.py
tests/test_lincs_cookiecutter.py
lincs_cookiecutter-0.1.1.dist-info/AUTHORS.rst
lincs_cookiecutter-0.1.1.dist-info/LICENSE
lincs_cookiecutter-0.1.1.dist-info/METADATA
lincs_cookiecutter-0.1.1.dist-info/WHEEL
lincs_cookiecutter-0.1.1.dist-info/top_level.txt
lincs_cookiecutter-0.1.1.dist-info/RECORD
