Metadata-Version: 2.1
Name: lincs-cookiecutter
Version: 0.1.1
Summary: This is a toy test to try cookiecutter2 during LINCS tutorial
Home-page: https://github.com/ibgp2/lincs_cookiecutter
Author: Marc-Olivier Buob
Author-email: marc-olivier.buob@nokia-bell-labs.com
License: GNU General Public License v3
Keywords: lincs_cookiecutter
Platform: UNKNOWN
Classifier: Development Status :: 2 - Pre-Alpha
Classifier: Intended Audience :: Developers
Classifier: License :: OSI Approved :: GNU General Public License v3 (GPLv3)
Classifier: Natural Language :: English
Classifier: Programming Language :: Python :: 3
Classifier: Programming Language :: Python :: 3.6
Classifier: Programming Language :: Python :: 3.7
Classifier: Programming Language :: Python :: 3.8
Requires-Python: >=3.6
License-File: LICENSE
License-File: AUTHORS.rst
